bearer_agent/__init__.py
bearer_agent/headers.py
bearer_agent/report_processor.py
bearer_agent/six.py
bearer_agent/version.py
bearer_agent/py2/__init__.py
bearer_agent/py2/agent.py
bearer_agent/py2/backoff.py
bearer_agent/py2/bodies.py
bearer_agent/py2/client.py
bearer_agent/py2/config.py
bearer_agent/py2/errors.py
bearer_agent/py2/matcher.py
bearer_agent/py2/remote_config.py
bearer_agent/py2/report.py
bearer_agent/py2/report_consumer.py
bearer_agent/py2/sanitize.py
bearer_agent/py2/shape_hash.py
bearer_agent/py2/util.py
bearer_agent/py2/filters/__init__.py
bearer_agent/py2/filters/base.py
bearer_agent/py2/filters/connection_error_filter.py
bearer_agent/py2/filters/domain_filter.py
bearer_agent/py2/filters/duration_filter.py
bearer_agent/py2/filters/filterset.py
bearer_agent/py2/filters/http_method_filter.py
bearer_agent/py2/filters/not_filter.py
bearer_agent/py2/filters/param_filter.py
bearer_agent/py2/filters/path_filter.py
bearer_agent/py2/filters/request_body_filter.py
bearer_agent/py2/filters/request_body_size_filter.py
bearer_agent/py2/filters/request_header_filter.py
bearer_agent/py2/filters/response_body_filter.py
bearer_agent/py2/filters/response_body_size_filter.py
bearer_agent/py2/filters/response_header_filter.py
bearer_agent/py2/filters/status_code_filter.py
bearer_agent/py2/hooks/__init__.py
bearer_agent/py2/hooks/intercept_http.py
bearer_agent/py2/hooks/intercept_twisted_web.py
bearer_agent/py2/hooks/intercept_urllib3.py
bearer_agent/py3/__init__.py
bearer_agent/py3/agent.py
bearer_agent/py3/backoff.py
bearer_agent/py3/bodies.py
bearer_agent/py3/client.py
bearer_agent/py3/config.py
bearer_agent/py3/errors.py
bearer_agent/py3/matcher.py
bearer_agent/py3/remote_config.py
bearer_agent/py3/report.py
bearer_agent/py3/report_consumer.py
bearer_agent/py3/sanitize.py
bearer_agent/py3/shape_hash.py
bearer_agent/py3/util.py
bearer_agent/py3/filters/__init__.py
bearer_agent/py3/filters/base.py
bearer_agent/py3/filters/connection_error_filter.py
bearer_agent-1.1.2.dist-info/LICENSE
bearer_agent-1.1.2.dist-info/METADATA
bearer_agent-1.1.2.dist-info/WHEEL
bearer_agent-1.1.2.dist-info/top_level.txt
bearer_agent-1.1.2.dist-info/RECORD
